spinvis/__init__.py
spinvis/_version.py
spinvis/spinVis_camera.py
spinvis/spinVis_coor.py
spinvis/spinVis_gui.py
spinvis-0.3.0.dist-info/LICENSE
spinvis-0.3.0.dist-info/METADATA
spinvis-0.3.0.dist-info/WHEEL
spinvis-0.3.0.dist-info/entry_points.txt
spinvis-0.3.0.dist-info/top_level.txt
spinvis-0.3.0.dist-info/RECORD
